trickster/__init__.py
trickster/api_app.py
trickster/collections.py
trickster/config.py
trickster/endpoints.py
trickster/sys.py
trickster/validation.py
trickster-2.0.2.dist-info/METADATA
trickster-2.0.2.dist-info/WHEEL
trickster-2.0.2.dist-info/entry_points.txt
trickster-2.0.2.dist-info/top_level.txt
trickster-2.0.2.dist-info/RECORD
